xrdump/__init__.py
xrdump/__main__.py
xrdump/zarr2nc.py
xrdump-0.1.0.dist-info/METADATA
xrdump-0.1.0.dist-info/WHEEL
xrdump-0.1.0.dist-info/entry_points.txt
xrdump-0.1.0.dist-info/top_level.txt
xrdump-0.1.0.dist-info/RECORD
